aprsd_admin_extension/__init__.py
aprsd_admin_extension/extension.py
aprsd_admin_extension/utils.py
aprsd_admin_extension/wsgi.py
aprsd_admin_extension/cmds/__init__.py
aprsd_admin_extension/cmds/web.py
aprsd_admin_extension/conf/__init__.py
aprsd_admin_extension/conf/main.py
aprsd_admin_extension/conf/opts.py
aprsd_admin_extension/threads/log_monitor.py
aprsd_admin_extension/web/.DS_Store
aprsd_admin_extension/web/__init__.py
aprsd_admin_extension/web/admin/__init__.py
aprsd_admin_extension/web/admin/static/css/index.css
aprsd_admin_extension/web/admin/static/css/prism.css
aprsd_admin_extension/web/admin/static/css/tabs.css
aprsd_admin_extension/web/admin/static/images/Untitled.png
aprsd_admin_extension/web/admin/static/images/aprs-symbols-16-0.png
aprsd_admin_extension/web/admin/static/images/aprs-symbols-16-1.png
aprsd_admin_extension/web/admin/static/images/aprs-symbols-64-0.png
aprsd_admin_extension/web/admin/static/images/aprs-symbols-64-1.png
aprsd_admin_extension/web/admin/static/images/aprs-symbols-64-2.png
aprsd_admin_extension/web/admin/static/js/charts.js
aprsd_admin_extension/web/admin/static/js/echarts.js
aprsd_admin_extension/web/admin/static/js/logs.js
aprsd_admin_extension/web/admin/static/js/main.js
aprsd_admin_extension/web/admin/static/js/prism.js
aprsd_admin_extension/web/admin/static/js/send-message.js
aprsd_admin_extension/web/admin/static/js/tabs.js
aprsd_admin_extension/web/admin/templates/index.html
aprsd_admin_extension-1.0.2.dist-info/licenses/LICENSE
aprsd_admin_extension-1.0.2.dist-info/METADATA
aprsd_admin_extension-1.0.2.dist-info/WHEEL
aprsd_admin_extension-1.0.2.dist-info/entry_points.txt
aprsd_admin_extension-1.0.2.dist-info/top_level.txt
aprsd_admin_extension-1.0.2.dist-info/RECORD
