Metadata-Version: 2.4
Name: aprsd-admin-extension
Version: 1.0.2
Summary: Administration extension for the Ham radio APRSD Server
Author-email: "Walter A. Boring IV" <waboring@hemna.com>
Maintainer-email: "Walter A. Boring IV" <waboring@hemna.com>
License: 
Project-URL: Homepage, https://github.com/hemna/aprsd-admin-extension
Project-URL: Bug Reports, https://github.com/hemna/aprsd-admin-extension/issues
Project-URL: Source, https://github.com/hemna/aprsd-admin-extension
Keywords: aprs,aprs-is,aprsd,aprsd-server,aprsd-client,aprsd-socket,aprsd-socket-server,aprsd-socket-client
Classifier: Development Status :: 5 - Production/Stable
Classifier: Environment :: Console
Classifier: Intended Audience :: Developers
Classifier: Intended Audience :: End Users/Desktop
Classifier: Intended Audience :: Information Technology
Classifier: Topic :: Communications :: Ham Radio
Classifier: Topic :: Internet
Classifier: Programming Language :: Python :: 3 :: Only
Classifier: Programming Language :: Python :: 3
Classifier: Programming Language :: Python :: 3.8
Classifier: Programming Language :: Python :: 3.9
Classifier: Programming Language :: Python :: 3.10
Classifier: Programming Language :: Python :: 3.11
Requires-Python: >=3.8
License-File: LICENSE
Requires-Dist: aprsd>=3.4.0
Requires-Dist: click
Requires-Dist: flask
Requires-Dist: Flask-HTTPAuth
Requires-Dist: oslo_config
Requires-Dist: python-socketio
Requires-Dist: werkzeug
Provides-Extra: dev
Requires-Dist: pip; extra == "dev"
Requires-Dist: pip-tools; extra == "dev"
Requires-Dist: bump2version; extra == "dev"
Requires-Dist: wheel; extra == "dev"
Requires-Dist: watchdog; extra == "dev"
Requires-Dist: flake8; extra == "dev"
Requires-Dist: tox; extra == "dev"
Requires-Dist: coverage; extra == "dev"
Requires-Dist: Sphinx; extra == "dev"
Requires-Dist: twine; extra == "dev"
Requires-Dist: pytest==6.2.5; extra == "dev"
Requires-Dist: gray; extra == "dev"
Dynamic: license-file
